{
	"name": "RGB",
	"manufacturer": "Generic",
	"productPage": "",
	"pixels": 1,
	"channels": {
        "Red": {
			"defaultValue": 0,
			"type": "color"
		},
		"Fine Red": {
			"defaultValue": 0,
			"type": "color"
		},
        "Green": {
			"defaultValue": 0,
			"type": "color"
		},
		"Fine Green": {
			"defaultValue": 0,
			"type": "color"
		},
        "Blue": {
			"defaultValue": 0,
			"type": "color"
		},
		"Fine Blue": {
			"defaultValue": 0,
			"type": "color"
		}
	},
	"modes": {
        "3 Channel": [
            "Red",
            "Green",
            "Blue"
        ],
		"6 Channel": [
			"Red",
			"Fine Red",
			"Green",
			"Fine Green",
			"Blue",
			"Fine Blue"
		]
	}
}
